spire/__init__.py
spire/ocr/ConfigureOptions.py
spire/ocr/OCRImageFormat.py
spire/ocr/OCRText.py
spire/ocr/OCRTextBlock.py
spire/ocr/OcrScanner.py
spire/ocr/TextBlockType.py
spire/ocr/VisualTextAligner.py
spire/ocr/__init__.py
spire/ocr/common/Boolean.py
spire/ocr/common/Byte.py
spire/ocr/common/Char.py
spire/ocr/common/Color.py
spire/ocr/common/Common.py
spire/ocr/common/CultureInfo.py
spire/ocr/common/DateTime.py
spire/ocr/common/Double.py
spire/ocr/common/EmfType.py
spire/ocr/common/Encoding.py
spire/ocr/common/FontStyle.py
spire/ocr/common/GraphicsUnit.py
spire/ocr/common/ICollection.py
spire/ocr/common/IDictionary.py
spire/ocr/common/IEnumerable.py
spire/ocr/common/IEnumerator.py
spire/ocr/common/IList.py
spire/ocr/common/Int16.py
spire/ocr/common/Int32.py
spire/ocr/common/Int64.py
spire/ocr/common/License.py
spire/ocr/common/PixelFormat.py
spire/ocr/common/Point.py
spire/ocr/common/PointF.py
spire/ocr/common/Rectangle.py
spire/ocr/common/RectangleF.py
spire/ocr/common/Regex.py
spire/ocr/common/RegexOptions.py
spire/ocr/common/Single.py
spire/ocr/common/Size.py
spire/ocr/common/SizeF.py
spire/ocr/common/SpireObject.py
spire/ocr/common/Stream.py
spire/ocr/common/String.py
spire/ocr/common/TimeSpan.py
spire/ocr/common/UInt16.py
spire/ocr/common/UInt32.py
spire/ocr/common/UInt64.py
spire/ocr/common/__init__.py
spire/ocr/lib/Spire.Ocr.Base.dylib
spire/ocr/lib/__init__.py
spire/ocr/lib/libSkiaSharp.dylib
spire/ocr/license/LicenseProvider.py
spire/ocr/license/__init__.py
spire_ocr-1.9.13.dist-info/METADATA
spire_ocr-1.9.13.dist-info/WHEEL
spire_ocr-1.9.13.dist-info/top_level.txt
spire_ocr-1.9.13.dist-info/RECORD
