Metadata-Version: 2.1
Name: spire-ocr
Version: 1.9.13
Summary: Spire.OCR for Python is a professional OCR component used to read text in image formats such as JPG,PNG,GIF,BMP, and TIFF
Home-page: https://www.e-iceblue.com
Author: E-iceblue
Author-email: sales@e-iceblue.com
Classifier: Programming Language :: Python :: 3.6
Classifier: License :: Free To Use But Restricted
Classifier: License :: Other/Proprietary License
Classifier: Operating System :: Microsoft :: Windows
Classifier: Operating System :: POSIX :: Linux
Classifier: Operating System :: Unix
Requires-Python: >=3.7
Requires-Dist: plum-dispatch ==1.7.4
